.gitignore
.pypirc
Data Generation Prototype.ipynb
Federated_Learning_Simulation.ipynb
README.md
Using the Runner.ipynb
requirements.txt
setup.py
datasets/blob_S20000_L3_F4_U100.csv
mozfldp/__init__.py
mozfldp/random_data_gen.py
mozfldp/runner.py
mozfldp/simulation_util.py
mozilla_fldp.egg-info/PKG-INFO
mozilla_fldp.egg-info/SOURCES.txt
mozilla_fldp.egg-info/dependency_links.txt
mozilla_fldp.egg-info/not-zip-safe
mozilla_fldp.egg-info/top_level.txt
server/mozfldp/simulation_util.py
tests/__init__.py
tests/test_simulation_util.py