Metadata-Version: 1.1
Name: mozilla-fldp
Version: 0.1.0
Summary: Federated Learning Experimentation
Home-page: https://github.com/mozilla/CANOSP-2019
Author: Mozilla Corporation
Author-email: dzeber@mozilla.com
License: MPL 2.0
Platform: UNKNOWN
Classifier: Development Status :: 3 - Alpha
Classifier: Environment :: Web Environment :: Mozilla
Classifier: Intended Audience :: Developers
Classifier: License :: OSI Approved :: Mozilla Public License 2.0 (MPL 2.0)
Classifier: Programming Language :: Python
Classifier: Programming Language :: Python :: 3
Classifier: Topic :: Scientific/Engineering :: Information Analysis
